<?xml version="1.0" encoding="UTF-8"?>
<persistence xmlns="http://java.sun.com/xml/ns/persistence">

    <persistence-unit name="SimplestCalculator">
        <class>Database.Entities.OperationsEntity</class>
        <class>Database.Entities.StatementsEntity</class>
        <properties>

            <property name="javax.persistence.jdbc.url" value="jdbc:mysql://localhost:3306"/>
            <property name="javax.persistence.jdbc.driver" value="com.mysql.jdbc.Driver"/>
            <property name="javax.persistence.jdbc.user" value="username"/>
            <property name="javax.persistence.jdbc.password" value="password"/>

            <property name="hibernate.archive.autodetection" value="class"/>
            <property name="hibernate.show_sql" value="true"/>
            <property name="hibernate.format_sql" value="true"/>
            <property name="hbm2ddl.auto" value="update"/>

        </properties>
    </persistence-unit>
</persistence>
